{
  "experiment": "baselines_lstm",
  "validation_type": "stratified_random",
  "mat_path": "D:\\xidian_Master\\研究生论文\\毕业论文\\xduts-main\\非核心文件\\绘图\\第三章\\20260304\\processedVehicleData_3class_REAL (2).mat",
  "L": 176,
  "preset": "paper_fair",
  "train_preset": {
    "lr": 0.0005,
    "weight_decay": 0.0001,
    "max_epochs": 200,
    "patience": 30
  },
  "oversample": false,
  "batch_size": 64,
  "n_runs": 1,
  "models": [
    "fixed_cnn_1d",
    "lstm_h64",
    "lstm_h32"
  ],
  "class_counts": [
    683,
    410,
    273
  ],
  "split_meta": [
    {
      "run_id": 0,
      "seed": 42,
      "split_hash": "4fe30d21181b8f91",
      "split_counts": {
        "train": [
          478,
          287,
          191
        ],
        "val": [
          102,
          62,
          41
        ],
        "test": [
          103,
          61,
          41
        ]
      }
    }
  ],
  "metrics": [
    {
      "experiment": "baselines_lstm",
      "validation_type": "stratified_random",
      "preset": "paper_fair",
      "oversample": 0,
      "run_id": 0,
      "seed": 42,
      "model": "fixed_cnn_1d",
      "param_count": 36323,
      "best_epoch": 188,
      "val_acc": 0.9463414634146341,
      "val_macro_f1": 0.9455816097795257,
      "test_acc": 0.9317073170731708,
      "test_macro_f1": 0.9253403465346536
    },
    {
      "experiment": "baselines_lstm",
      "validation_type": "stratified_random",
      "preset": "paper_fair",
      "oversample": 0,
      "run_id": 0,
      "seed": 42,
      "model": "lstm_h64",
      "param_count": 51395,
      "best_epoch": 106,
      "val_acc": 0.8390243902439024,
      "val_macro_f1": 0.8216586019774587,
      "test_acc": 0.8195121951219512,
      "test_macro_f1": 0.7993058888456112
    },
    {
      "experiment": "baselines_lstm",
      "validation_type": "stratified_random",
      "preset": "paper_fair",
      "oversample": 0,
      "run_id": 0,
      "seed": 42,
      "model": "lstm_h32",
      "param_count": 13411,
      "best_epoch": 123,
      "val_acc": 0.848780487804878,
      "val_macro_f1": 0.8467150254765835,
      "test_acc": 0.8,
      "test_macro_f1": 0.7884444444444445
    }
  ],
  "summary": [
    {
      "model": "fixed_cnn_1d",
      "runs": 1,
      "param_count": 36323,
      "test_acc_mean": 0.9317073170731708,
      "test_acc_std": 0.0,
      "test_macro_f1_mean": 0.9253403465346536,
      "test_macro_f1_std": 0.0,
      "val_macro_f1_mean": 0.9455816097795257,
      "val_macro_f1_std": 0.0
    },
    {
      "model": "lstm_h32",
      "runs": 1,
      "param_count": 13411,
      "test_acc_mean": 0.8,
      "test_acc_std": 0.0,
      "test_macro_f1_mean": 0.7884444444444445,
      "test_macro_f1_std": 0.0,
      "val_macro_f1_mean": 0.8467150254765835,
      "val_macro_f1_std": 0.0
    },
    {
      "model": "lstm_h64",
      "runs": 1,
      "param_count": 51395,
      "test_acc_mean": 0.8195121951219512,
      "test_acc_std": 0.0,
      "test_macro_f1_mean": 0.7993058888456112,
      "test_macro_f1_std": 0.0,
      "val_macro_f1_mean": 0.8216586019774587,
      "val_macro_f1_std": 0.0
    }
  ],
  "model_results": [
    {
      "run_id": 0,
      "seed": 42,
      "models": [
        {
          "model": "fixed_cnn_1d",
          "param_count": 36323,
          "train_seconds": 61.6813542842865,
          "result": {
            "best_epoch": 188,
            "val": {
              "accuracy": 0.9463414634146341,
              "macro_f1": 0.9455816097795257,
              "per_class": [
                {
                  "class_id": 0,
                  "class_name": "small",
                  "precision": 0.97,
                  "recall": 0.9509803921568627,
                  "f1": 0.9603960396039604,
                  "support": 102
                },
                {
                  "class_id": 1,
                  "class_name": "medium",
                  "precision": 0.8923076923076924,
                  "recall": 0.9354838709677419,
                  "f1": 0.9133858267716536,
                  "support": 62
                },
                {
                  "class_id": 2,
                  "class_name": "large",
                  "precision": 0.975,
                  "recall": 0.9512195121951219,
                  "f1": 0.9629629629629629,
                  "support": 41
                }
              ],
              "confusion_matrix": [
                [
                  97,
                  5,
                  0
                ],
                [
                  3,
                  58,
                  1
                ],
                [
                  0,
                  2,
                  39
                ]
              ]
            },
            "test": {
              "accuracy": 0.9317073170731708,
              "macro_f1": 0.9253403465346536,
              "per_class": [
                {
                  "class_id": 0,
                  "class_name": "small",
                  "precision": 0.9797979797979798,
                  "recall": 0.941747572815534,
                  "f1": 0.9603960396039605,
                  "support": 103
                },
                {
                  "class_id": 1,
                  "class_name": "medium",
                  "precision": 0.8507462686567164,
                  "recall": 0.9344262295081968,
                  "f1": 0.8906250000000001,
                  "support": 61
                },
                {
                  "class_id": 2,
                  "class_name": "large",
                  "precision": 0.9487179487179487,
                  "recall": 0.9024390243902439,
                  "f1": 0.9249999999999999,
                  "support": 41
                }
              ],
              "confusion_matrix": [
                [
                  97,
                  6,
                  0
                ],
                [
                  2,
                  57,
                  2
                ],
                [
                  0,
                  4,
                  37
                ]
              ]
            },
            "y_pred_val": [
              0,
              0,
              0,
              0,
              0,
              0,
              0,
              0,
              0,
              0,
              0,
              0,
              0,
              0,
              0,
              1,
              0,
              0,
              1,
              0,
              0,
              0,
              0,
              0,
              0,
              0,
              1,
              0,
              0,
              0,
              0,
              0,
              0,
              0,
              0,
              0,
              1,
              0,
              0,
              0,
              0,
              0,
              0,
              0,
              0,
              0,
              0,
              0,
              0,
              0,
              0,
              0,
              0,
              0,
              0,
              0,
              0,
              0,
              0,
              0,
              0,
              0,
              0,
              0,
              0,
              0,
              0,
              0,
              0,
              0,
              0,
              0,
              0,
              0,
              0,
              0,
              0,
              0,
              0,
              0,
              0,
              0,
              0,
              0,
              0,
              0,
              0,
              0,
              0,
              1,
              0,
              0,
              0,
              0,
              0,
              0,
              0,
              0,
              0,
              0,
              0,
              0,
              1,
              1,
              1,
              0,
              1,
              1,
              1,
              1,
              0,
              1,
              1,
              1,
              1,
              1,
              1,
              1,
              1,
              1,
              1,
              1,
              1,
              1,
              1,
              1,
              1,
              1,
              1,
              1,
              1,
              1,
              1,
              0,
              1,
              1,
              1,
              1,
              1,
              1,
              1,
              1,
              1,
              1,
              1,
              1,
              1,
              1,
              1,
              1,
              1,
              1,
              1,
              2,
              1,
              1,
              1,
              1,
              1,
              1,
              1,
              1,
              1,
              1,
              2,
              2,
              2,
              2,
              2,
              2,
              2,
              2,
              2,
              2,
              1,
              2,
              2,
              2,
              2,
              2,
              2,
              2,
              1,
              2,
              2,
              2,
              2,
              2,
              2,
              2,
              2,
              2,
              2,
              2,
              2,
              2,
              2,
              2,
              2,
              2,
              2,
              2,
              2,
              2,
              2
            ],
            "y_pred_test": [
              0,
              0,
              1,
              0,
              0,
              0,
              0,
              0,
              0,
              0,
              0,
              0,
              1,
              0,
              0,
              0,
              0,
              0,
              0,
              0,
              0,
              0,
              1,
              0,
              0,
              0,
              0,
              0,
              0,
              0,
              0,
              0,
              0,
              0,
              0,
              0,
              0,
              0,
              0,
              0,
              0,
              0,
              0,
              0,
              1,
              1,
              0,
              0,
              0,
              0,
              0,
              0,
              0,
              0,
              0,
              0,
              0,
              0,
              0,
              0,
              0,
              0,
              0,
              0,
              0,
              0,
              0,
              0,
              0,
              0,
              0,
              0,
              0,
              0,
              0,
              0,
              0,
              0,
              0,
              0,
              0,
              0,
              0,
              0,
              0,
              0,
              0,
              0,
              0,
              1,
              0,
              0,
              0,
              0,
              0,
              0,
              0,
              0,
              0,
              0,
              0,
              0,
              0,
              1,
              1,
              1,
              1,
              1,
              0,
              1,
              1,
              1,
              1,
              1,
              1,
              1,
              1,
              1,
              1,
              1,
              1,
              1,
              1,
              1,
              0,
              1,
              1,
              1,
              1,
              1,
              1,
              1,
              1,
              1,
              1,
              1,
              1,
              1,
              1,
              2,
              1,
              1,
              1,
              1,
              1,
              1,
              1,
              1,
              1,
              1,
              1,
              1,
              1,
              1,
              1,
              1,
              2,
              1,
              1,
              1,
              1,
              1,
              1,
              1,
              2,
              2,
              2,
              2,
              2,
              2,
              2,
              2,
              2,
              2,
              2,
              2,
              2,
              2,
              2,
              2,
              2,
              2,
              2,
              1,
              2,
              2,
              2,
              2,
              2,
              2,
              1,
              2,
              2,
              2,
              2,
              2,
              2,
              1,
              2,
              2,
              2,
              2,
              2,
              1,
              2
            ],
            "device": "cuda"
          }
        },
        {
          "model": "lstm_h64",
          "param_count": 51395,
          "train_seconds": 6.962907552719116,
          "result": {
            "best_epoch": 106,
            "val": {
              "accuracy": 0.8390243902439024,
              "macro_f1": 0.8216586019774587,
              "per_class": [
                {
                  "class_id": 0,
                  "class_name": "small",
                  "precision": 0.8571428571428571,
                  "recall": 0.9411764705882353,
                  "f1": 0.897196261682243,
                  "support": 102
                },
                {
                  "class_id": 1,
                  "class_name": "medium",
                  "precision": 0.8163265306122449,
                  "recall": 0.6451612903225806,
                  "f1": 0.7207207207207208,
                  "support": 62
                },
                {
                  "class_id": 2,
                  "class_name": "large",
                  "precision": 0.8181818181818182,
                  "recall": 0.8780487804878049,
                  "f1": 0.8470588235294119,
                  "support": 41
                }
              ],
              "confusion_matrix": [
                [
                  96,
                  6,
                  0
                ],
                [
                  14,
                  40,
                  8
                ],
                [
                  2,
                  3,
                  36
                ]
              ]
            },
            "test": {
              "accuracy": 0.8195121951219512,
              "macro_f1": 0.7993058888456112,
              "per_class": [
                {
                  "class_id": 0,
                  "class_name": "small",
                  "precision": 0.8434782608695652,
                  "recall": 0.941747572815534,
                  "f1": 0.8899082568807339,
                  "support": 103
                },
                {
                  "class_id": 1,
                  "class_name": "medium",
                  "precision": 0.7307692307692307,
                  "recall": 0.6229508196721312,
                  "f1": 0.672566371681416,
                  "support": 61
                },
                {
                  "class_id": 2,
                  "class_name": "large",
                  "precision": 0.868421052631579,
                  "recall": 0.8048780487804879,
                  "f1": 0.8354430379746836,
                  "support": 41
                }
              ],
              "confusion_matrix": [
                [
                  97,
                  6,
                  0
                ],
                [
                  18,
                  38,
                  5
                ],
                [
                  0,
                  8,
                  33
                ]
              ]
            },
            "y_pred_val": [
              0,
              0,
              0,
              1,
              0,
              0,
              0,
              0,
              1,
              0,
              0,
              0,
              0,
              0,
              0,
              1,
              0,
              0,
              1,
              0,
              0,
              0,
              0,
              0,
              0,
              0,
              0,
              0,
              0,
              0,
              0,
              0,
              0,
              0,
              0,
              0,
              0,
              0,
              0,
              0,
              0,
              0,
              0,
              0,
              0,
              0,
              0,
              0,
              0,
              0,
              0,
              0,
              0,
              0,
              0,
              0,
              0,
              0,
              0,
              0,
              1,
              0,
              0,
              0,
              0,
              0,
              0,
              0,
              0,
              0,
              0,
              0,
              0,
              0,
              0,
              0,
              0,
              0,
              0,
              0,
              0,
              0,
              0,
              0,
              0,
              0,
              0,
              0,
              0,
              1,
              0,
              0,
              0,
              0,
              0,
              0,
              0,
              0,
              0,
              0,
              0,
              0,
              1,
              1,
              1,
              0,
              1,
              1,
              1,
              1,
              1,
              1,
              2,
              0,
              1,
              2,
              2,
              0,
              0,
              1,
              1,
              1,
              1,
              1,
              1,
              0,
              1,
              1,
              1,
              1,
              1,
              1,
              1,
              0,
              0,
              1,
              0,
              1,
              0,
              1,
              0,
              1,
              2,
              0,
              2,
              1,
              2,
              2,
              1,
              0,
              1,
              1,
              1,
              2,
              1,
              1,
              1,
              1,
              1,
              1,
              1,
              0,
              1,
              0,
              2,
              2,
              2,
              2,
              1,
              2,
              2,
              2,
              2,
              2,
              1,
              2,
              2,
              2,
              2,
              2,
              1,
              2,
              2,
              2,
              2,
              2,
              2,
              2,
              2,
              2,
              2,
              2,
              2,
              2,
              2,
              0,
              2,
              2,
              2,
              0,
              2,
              2,
              2,
              2,
              2
            ],
            "y_pred_test": [
              0,
              1,
              1,
              1,
              0,
              0,
              0,
              0,
              0,
              0,
              0,
              0,
              0,
              0,
              0,
              0,
              0,
              0,
              0,
              0,
              0,
              0,
              0,
              0,
              0,
              0,
              0,
              0,
              0,
              0,
              0,
              0,
              0,
              0,
              0,
              0,
              0,
              0,
              0,
              0,
              0,
              0,
              0,
              0,
              0,
              0,
              0,
              0,
              0,
              0,
              0,
              0,
              0,
              0,
              0,
              0,
              1,
              0,
              0,
              0,
              0,
              0,
              0,
              0,
              0,
              0,
              0,
              0,
              0,
              0,
              0,
              0,
              0,
              0,
              0,
              0,
              0,
              1,
              0,
              0,
              0,
              1,
              0,
              0,
              0,
              0,
              0,
              0,
              0,
              0,
              0,
              0,
              0,
              0,
              0,
              0,
              0,
              0,
              0,
              0,
              0,
              0,
              0,
              1,
              1,
              1,
              0,
              1,
              0,
              1,
              1,
              0,
              1,
              1,
              1,
              1,
              1,
              1,
              1,
              1,
              1,
              1,
              1,
              2,
              0,
              0,
              1,
              1,
              1,
              1,
              1,
              0,
              1,
              0,
              1,
              1,
              0,
              1,
              0,
              1,
              0,
              2,
              2,
              1,
              1,
              0,
              1,
              1,
              0,
              0,
              0,
              1,
              1,
              1,
              1,
              1,
              2,
              0,
              0,
              2,
              1,
              1,
              0,
              0,
              2,
              2,
              2,
              2,
              2,
              2,
              2,
              1,
              2,
              2,
              2,
              2,
              2,
              2,
              2,
              1,
              2,
              2,
              2,
              1,
              2,
              2,
              2,
              2,
              2,
              2,
              1,
              2,
              2,
              2,
              1,
              2,
              2,
              1,
              2,
              2,
              2,
              2,
              2,
              1,
              1
            ],
            "device": "cuda"
          }
        },
        {
          "model": "lstm_h32",
          "param_count": 13411,
          "train_seconds": 7.683733940124512,
          "result": {
            "best_epoch": 123,
            "val": {
              "accuracy": 0.848780487804878,
              "macro_f1": 0.8467150254765835,
              "per_class": [
                {
                  "class_id": 0,
                  "class_name": "small",
                  "precision": 0.9166666666666666,
                  "recall": 0.8627450980392157,
                  "f1": 0.888888888888889,
                  "support": 102
                },
                {
                  "class_id": 1,
                  "class_name": "medium",
                  "precision": 0.7313432835820896,
                  "recall": 0.7903225806451613,
                  "f1": 0.7596899224806203,
                  "support": 62
                },
                {
                  "class_id": 2,
                  "class_name": "large",
                  "precision": 0.8809523809523809,
                  "recall": 0.9024390243902439,
                  "f1": 0.8915662650602411,
                  "support": 41
                }
              ],
              "confusion_matrix": [
                [
                  88,
                  14,
                  0
                ],
                [
                  8,
                  49,
                  5
                ],
                [
                  0,
                  4,
                  37
                ]
              ]
            },
            "test": {
              "accuracy": 0.8,
              "macro_f1": 0.7884444444444445,
              "per_class": [
                {
                  "class_id": 0,
                  "class_name": "small",
                  "precision": 0.8504672897196262,
                  "recall": 0.883495145631068,
                  "f1": 0.8666666666666667,
                  "support": 103
                },
                {
                  "class_id": 1,
                  "class_name": "medium",
                  "precision": 0.65625,
                  "recall": 0.6885245901639344,
                  "f1": 0.672,
                  "support": 61
                },
                {
                  "class_id": 2,
                  "class_name": "large",
                  "precision": 0.9117647058823529,
                  "recall": 0.7560975609756098,
                  "f1": 0.8266666666666665,
                  "support": 41
                }
              ],
              "confusion_matrix": [
                [
                  91,
                  12,
                  0
                ],
                [
                  16,
                  42,
                  3
                ],
                [
                  0,
                  10,
                  31
                ]
              ]
            },
            "y_pred_val": [
              0,
              0,
              1,
              0,
              0,
              0,
              0,
              0,
              1,
              0,
              0,
              0,
              0,
              0,
              0,
              1,
              0,
              0,
              1,
              0,
              0,
              0,
              0,
              1,
              0,
              0,
              0,
              0,
              0,
              0,
              0,
              0,
              1,
              0,
              0,
              0,
              1,
              0,
              0,
              0,
              0,
              0,
              0,
              1,
              0,
              0,
              0,
              0,
              0,
              0,
              1,
              0,
              0,
              0,
              0,
              0,
              0,
              0,
              0,
              0,
              1,
              0,
              0,
              0,
              0,
              0,
              0,
              0,
              0,
              0,
              0,
              0,
              0,
              0,
              0,
              0,
              0,
              0,
              0,
              0,
              0,
              0,
              0,
              0,
              0,
              0,
              0,
              0,
              1,
              1,
              0,
              0,
              0,
              1,
              0,
              1,
              0,
              0,
              0,
              0,
              0,
              0,
              1,
              1,
              1,
              1,
              1,
              1,
              1,
              1,
              0,
              1,
              1,
              0,
              1,
              2,
              2,
              0,
              0,
              1,
              1,
              1,
              1,
              1,
              1,
              1,
              1,
              1,
              1,
              1,
              1,
              1,
              1,
              1,
              1,
              1,
              0,
              1,
              0,
              1,
              1,
              1,
              1,
              1,
              2,
              1,
              1,
              1,
              1,
              0,
              1,
              2,
              1,
              1,
              1,
              1,
              1,
              1,
              1,
              2,
              1,
              0,
              1,
              1,
              2,
              2,
              2,
              2,
              2,
              2,
              2,
              1,
              2,
              2,
              2,
              2,
              2,
              2,
              2,
              2,
              1,
              2,
              1,
              2,
              2,
              2,
              2,
              2,
              2,
              2,
              2,
              2,
              2,
              2,
              2,
              1,
              2,
              2,
              2,
              2,
              2,
              2,
              2,
              2,
              2
            ],
            "y_pred_test": [
              0,
              1,
              1,
              1,
              0,
              0,
              0,
              0,
              0,
              0,
              0,
              0,
              0,
              0,
              0,
              0,
              0,
              0,
              0,
              0,
              0,
              0,
              0,
              0,
              0,
              0,
              0,
              1,
              0,
              0,
              0,
              0,
              0,
              0,
              0,
              0,
              0,
              0,
              0,
              1,
              0,
              0,
              0,
              0,
              0,
              0,
              0,
              0,
              1,
              0,
              0,
              0,
              0,
              0,
              0,
              0,
              1,
              0,
              0,
              0,
              0,
              0,
              0,
              0,
              0,
              1,
              0,
              0,
              0,
              0,
              0,
              0,
              0,
              0,
              0,
              0,
              0,
              1,
              0,
              0,
              1,
              0,
              0,
              0,
              0,
              0,
              0,
              1,
              0,
              0,
              0,
              0,
              1,
              0,
              0,
              0,
              0,
              0,
              0,
              0,
              0,
              0,
              0,
              1,
              0,
              1,
              1,
              1,
              0,
              1,
              1,
              0,
              1,
              1,
              1,
              1,
              1,
              1,
              0,
              1,
              0,
              1,
              1,
              1,
              0,
              0,
              1,
              1,
              1,
              1,
              1,
              1,
              1,
              0,
              1,
              1,
              0,
              1,
              0,
              2,
              1,
              1,
              1,
              0,
              1,
              0,
              1,
              1,
              0,
              1,
              1,
              1,
              1,
              1,
              1,
              1,
              2,
              0,
              1,
              2,
              1,
              0,
              0,
              1,
              2,
              2,
              2,
              2,
              2,
              2,
              2,
              1,
              1,
              2,
              2,
              2,
              2,
              2,
              1,
              1,
              2,
              2,
              2,
              2,
              2,
              2,
              2,
              2,
              2,
              2,
              2,
              2,
              2,
              2,
              1,
              2,
              1,
              1,
              2,
              1,
              2,
              2,
              2,
              1,
              1
            ],
            "device": "cuda"
          }
        }
      ]
    }
  ]
}